axcontrol/__init__.py
axcontrol/app.py
axcontrol/automation/__init__.py
axcontrol/automation/app_launcher.py
axcontrol/automation/checks.py
axcontrol/automation/control_finder.py
axcontrol/automation/control_finder_manager.py
axcontrol/automation/interact.py
axcontrol/code_generator/__init__.py
axcontrol/code_generator/simple.py
axcontrol/gui/__init__.py
axcontrol/gui/app.py
axcontrol/gui/overlay.py
axcontrol/listeners/__init__.py
axcontrol/listeners/input.py
axcontrol/utils/__init__.py
axcontrol/utils/clipboard.py
axcontrol-0.1.6.dist-info/entry_points.txt
axcontrol-0.1.6.dist-info/LICENSE
axcontrol-0.1.6.dist-info/WHEEL
axcontrol-0.1.6.dist-info/METADATA
axcontrol-0.1.6.dist-info/RECORD
