Metadata-Version: 2.1
Name: axcontrol
Version: 0.1.6
Summary: AxControl is a Windows 10/11 UI Automation tool developed by aubex Gmbh, Hockenheim.
Author-email: Marius Räsener <marius.raesener@aubex.de>
Requires-Python: >=3.10
Classifier: Operating System :: Microsoft :: Windows
Classifier: Programming Language :: Python :: 3.10
Classifier: Programming Language :: Python :: 3.11
Classifier: Programming Language :: Python :: 3.12
Requires-Dist: uiautomation>=2.0.19
Requires-Dist: pynput>=1.7.7
Requires-Dist: pyperclip>=1.9.0
Requires-Dist: pywin32>=306
Project-URL: Source, https://github.com/aubex/axcontrol
